ecf_parser/__init__.py
ecf_parser/__main__.py
ecf_parser/backup.py
ecf_parser/parser.py
ecf_parser/patterns.py
ecf_parser/utils.py
ecf_parser-0.1.3.dist-info/METADATA
ecf_parser-0.1.3.dist-info/RECORD
ecf_parser-0.1.3.dist-info/WHEEL
ecf_parser-0.1.3.dist-info/entry_points.txt
ecf_parser-0.1.3.dist-info/top_level.txt
tests/__init__.py
tests/test_parser.py
